pretf/aws.py
pretf.aws-0.7.3.dist-info/METADATA
pretf.aws-0.7.3.dist-info/WHEEL
pretf.aws-0.7.3.dist-info/top_level.txt
pretf.aws-0.7.3.dist-info/RECORD
