Metadata-Version: 2.1
Name: pretf.aws
Version: 0.7.3
Summary: UNKNOWN
Home-page: UNKNOWN
Author: Raymond Butcher
Author-email: randomy@gmail.com
License: MIT License
Platform: UNKNOWN
Requires-Python: >=3.6
Requires-Dist: boto3
Requires-Dist: pretf
